redis_toolkit/__init__.py
redis_toolkit/core.py
redis_toolkit/exceptions.py
redis_toolkit/options.py
redis_toolkit/pool_manager.py
redis_toolkit/subscription_manager.py
redis_toolkit/converters/__init__.py
redis_toolkit/converters/audio.py
redis_toolkit/converters/errors.py
redis_toolkit/converters/image.py
redis_toolkit/converters/video.py
redis_toolkit/utils/__init__.py
redis_toolkit/utils/retry.py
redis_toolkit/utils/serializers.py
redis_toolkit-0.4.0.dist-info/licenses/LICENSE
redis_toolkit-0.4.0.dist-info/METADATA
redis_toolkit-0.4.0.dist-info/WHEEL
redis_toolkit-0.4.0.dist-info/top_level.txt
redis_toolkit-0.4.0.dist-info/RECORD
