Metadata-Version: 2.4
Name: redis-toolkit
Version: 0.4.0
Summary: Enhanced Redis wrapper with multi-type data support and pub/sub automation
Home-page: https://github.com/JonesHong/redis-toolkit
Author: JonesHong
Author-email: JonesHong <latte831104@gmail.com>
License: MIT
Project-URL: Homepage, https://github.com/JonesHong/redis-toolkit
Project-URL: Repository, https://github.com/JonesHong/redis-toolkit.git
Project-URL: Bug Reports, https://github.com/JonesHong/redis-toolkit/issues
Keywords: redis,toolkit,pubsub,serialization,buffer,audio,video,image,converter
Classifier: Development Status :: 4 - Beta
Classifier: Intended Audience :: Developers
Classifier: License :: OSI Approved :: MIT License
Classifier: Operating System :: OS Independent
Classifier: Programming Language :: Python :: 3
Classifier: Programming Language :: Python :: 3.7
Classifier: Programming Language :: Python :: 3.8
Classifier: Programming Language :: Python :: 3.9
Classifier: Programming Language :: Python :: 3.10
Classifier: Programming Language :: Python :: 3.11
Classifier: Topic :: Database
Classifier: Topic :: Software Development :: Libraries :: Python Modules
Classifier: Topic :: System :: Distributed Computing
Classifier: Topic :: Multimedia :: Graphics
Classifier: Topic :: Multimedia :: Sound/Audio
Classifier: Topic :: Multimedia :: Video
Requires-Python: >=3.7
License-File: LICENSE
Requires-Dist: redis>=4.0.0
Requires-Dist: pretty-loguru>=1.1.3
Provides-Extra: dev
Requires-Dist: pytest>=6.0; extra == "dev"
Requires-Dist: pytest-cov>=2.0; extra == "dev"
Requires-Dist: black>=21.0; extra == "dev"
Requires-Dist: flake8>=3.8; extra == "dev"
Requires-Dist: mypy>=0.910; extra == "dev"
Requires-Dist: pre-commit>=2.15; extra == "dev"
Provides-Extra: cv2
Requires-Dist: opencv-python>=4.5.0; extra == "cv2"
Requires-Dist: numpy>=1.19.0; extra == "cv2"
Provides-Extra: audio
Requires-Dist: numpy>=1.19.0; extra == "audio"
Requires-Dist: scipy>=1.7.0; extra == "audio"
Provides-Extra: audio-full
Requires-Dist: numpy>=1.19.0; extra == "audio-full"
Requires-Dist: scipy>=1.7.0; extra == "audio-full"
Requires-Dist: soundfile>=0.10.0; extra == "audio-full"
Provides-Extra: image
Requires-Dist: opencv-python>=4.5.0; extra == "image"
Requires-Dist: numpy>=1.19.0; extra == "image"
Requires-Dist: Pillow>=8.0.0; extra == "image"
Provides-Extra: video
Requires-Dist: opencv-python>=4.5.0; extra == "video"
Requires-Dist: numpy>=1.19.0; extra == "video"
Provides-Extra: media
Requires-Dist: opencv-python>=4.5.0; extra == "media"
Requires-Dist: numpy>=1.19.0; extra == "media"
Requires-Dist: scipy>=1.7.0; extra == "media"
Requires-Dist: soundfile>=0.10.0; extra == "media"
Requires-Dist: Pillow>=8.0.0; extra == "media"
Provides-Extra: all
Requires-Dist: opencv-python>=4.5.0; extra == "all"
Requires-Dist: numpy>=1.19.0; extra == "all"
Requires-Dist: scipy>=1.7.0; extra == "all"
Requires-Dist: soundfile>=0.10.0; extra == "all"
Requires-Dist: Pillow>=8.0.0; extra == "all"
Dynamic: author
Dynamic: home-page
Dynamic: license-file
Dynamic: requires-python
